vedro_unittest/__init__.py
vedro_unittest/_scenario_provider.py
vedro_unittest/_test_result.py
vedro_unittest/_vedro_unittest.py
vedro_unittest/py.typed
vedro_unittest-0.2.0.dist-info/licenses/LICENSE
vedro_unittest-0.2.0.dist-info/METADATA
vedro_unittest-0.2.0.dist-info/WHEEL
vedro_unittest-0.2.0.dist-info/top_level.txt
vedro_unittest-0.2.0.dist-info/RECORD
